reactivehub/__init__.py
reactivehub/reactivehub.py
reactivehub_sdk_python-0.2.dist-info/LICENSE
reactivehub_sdk_python-0.2.dist-info/METADATA
reactivehub_sdk_python-0.2.dist-info/WHEEL
reactivehub_sdk_python-0.2.dist-info/top_level.txt
reactivehub_sdk_python-0.2.dist-info/RECORD
